{
  "Enabled": true,
  "FogColor": {
    "a": 0.0,
    "r": 0.4117647,
    "g": 0.831372559,
    "b": 0.5882353
  },
  "FogDensity": 0.0002,
  "FogAmbience": 0.4,
  "DensityNoiseDirection": {
    "x": 0.0,
    "y": -1.0,
    "z": 0.0,
    "magnitude": 1.0,
    "sqrMagnitude": 1.0
  },
  "DensityNoiseSpeed": 0.02,
  "DensityNoiseScale": 0.131,
  "DensityHeightAltitude": 6.0,
  "DensityHeightRange": 3.0,
  "DensityHeightMaxBoost": 0.02,
  "Infection": 0.15,
  "name": "Fog_light_green_INFECTION_R3A2_high",
  "internalEnabled": true,
  "persistentID": 137
}