{
  "SkipLocalization": false,
  "MachineTranslation": false,
  "English": "FI-D <color=orange>D@YASPH3R& 741</color>",
  "Description": "",
  "CharacterMetaData": 1,
  "French": {
    "Translation": "TR0-VEZ L{ <color=orange>SPH3R& D= D0NN%ES\u00A0741</color>.",
    "ShouldTranslate": false
  },
  "Italian": {
    "Translation": "!ROVA£E <color=orange>$FE,A D@TI 741</color>",
    "ShouldTranslate": false
  },
  "German": {
    "Translation": "FI-D(N S1e d__ <color=orange>D@YTÉMKùg3l 741</color>.",
    "ShouldTranslate": false
  },
  "Spanish": {
    "Translation": "ENC-ENTRA LA <color=orange>ESF3RA DE DAT@S 741</color>.",
    "ShouldTranslate": false
  },
  "Russian": {
    "Translation": "НА?Д-ТЕ <color=orange>СФ#РУ Д@ННЫ>< 741</color>",
    "ShouldTranslate": false
  },
  "Portuguese_Brazil": {
    "Translation": "EN<ONTR4r- <color=orange>3SF=ER@ DE DªD0$ 741</color>",
    "ShouldTranslate": false
  },
  "Polish": {
    "Translation": "ZN_JD% <color=orange>SF3R3 D@N;CH 741</color>",
    "ShouldTranslate": false
  },
  "Japanese": {
    "Translation": "<color=orange>デー夕久フぃア 741</color>を見ツケろ",
    "ShouldTranslate": false
  },
  "Korean": {
    "Translation": "<color=orange>ㄷㅔ01Eㅓ스ㅍ10ㅓ</color> 찾ㅇ기",
    "ShouldTranslate": false
  },
  "Chinese_Traditional": {
    "Translation": "尋-找<color=orange>@YA料球741</color>",
    "ShouldTranslate": false
  },
  "Chinese_Simplified": {
    "Translation": "找$^&到_)^<color=orange>数(%据?#@球$&*741</color>",
    "ShouldTranslate": false
  },
  "ExportVersion": 2,
  "ImportVersion": 2,
  "name": "LevelLayoutData.Bridge_Glitch_R8B3",
  "internalEnabled": true,
  "persistentID": 210041075
}