{
  "SkipLocalization": false,
  "MachineTranslation": false,
  "English": "<color=red>://ERROR: Door in emergency lockdown, unable to operate.</color>",
  "Description": "A text string that appears on screen when the player attempts to open a door which is locked due to an emergency lockdown. Don't alter the RichText tags.",
  "CharacterMetaData": 3,
  "French": {
    "Translation": "<color=red>://ERREUR: La porte est bloquée par le verrouillage d'urgence, impossible de continuer.</color>",
    "ShouldTranslate": false
  },
  "Italian": {
    "Translation": "<color=red>://ERRORE: porta in blocco d'emergenza, impossibile azionare.</color>",
    "ShouldTranslate": false
  },
  "German": {
    "Translation": "<color=red>://FEHLER: Tür in Notverriegelung, keine Operation möglich.</color>",
    "ShouldTranslate": false
  },
  "Spanish": {
    "Translation": "<color=red>://ERROR: Puerta en cierre de emergencia. No se puede operar.</color>",
    "ShouldTranslate": false
  },
  "Russian": {
    "Translation": "<color=red>://ОШИБКА. Действует режим изоляции. Дверь заблокирована.</color>",
    "ShouldTranslate": false
  },
  "Portuguese_Brazil": {
    "Translation": "<color=red>://ERRO: Porta em confinamento de emergência, impossível operar.</color>",
    "ShouldTranslate": false
  },
  "Polish": {
    "Translation": "<color=red>://BŁĄD: Drzwi poddane blokadzie awaryjnej, sterowanie uniemożliwione.</color>",
    "ShouldTranslate": false
  },
  "Japanese": {
    "Translation": "<color=red>://エラー：ドアは緊急封鎖中。作動不可。</color>",
    "ShouldTranslate": false
  },
  "Korean": {
    "Translation": "<color=red>://오류: 문이 비상 폐쇄 상태여서 작동 불가능합니다.</color>",
    "ShouldTranslate": false
  },
  "Chinese_Traditional": {
    "Translation": "<color=red>://錯誤：門處於緊急封鎖狀態，無法操作。</color>",
    "ShouldTranslate": false
  },
  "Chinese_Simplified": {
    "Translation": "<color=red>://错误：门处于紧急封锁状态，无法操作。</color>",
    "ShouldTranslate": false
  },
  "ExportVersion": 3,
  "ImportVersion": 3,
  "name": "LevelLayoutData.ProgressionPuzzle.CustomText_R8B2",
  "internalEnabled": true,
  "persistentID": 3533936134
}