{
  "SkipLocalization": false,
  "MachineTranslation": false,
  "English": "Yoruba",
  "Description": "A language spoken in Nigeria.",
  "CharacterMetaData": 1,
  "French": {
    "Translation": "Yoruba",
    "ShouldTranslate": false
  },
  "Italian": {
    "Translation": "Yoruba",
    "ShouldTranslate": false
  },
  "German": {
    "Translation": "Yoruba",
    "ShouldTranslate": false
  },
  "Spanish": {
    "Translation": "Yoruba",
    "ShouldTranslate": false
  },
  "Russian": {
    "Translation": "Йоруба",
    "ShouldTranslate": false
  },
  "Portuguese_Brazil": {
    "Translation": "Ioruba",
    "ShouldTranslate": false
  },
  "Polish": {
    "Translation": "Joruba",
    "ShouldTranslate": false
  },
  "Japanese": {
    "Translation": "ヨルバ語",
    "ShouldTranslate": false
  },
  "Korean": {
    "Translation": "요루바어",
    "ShouldTranslate": false
  },
  "Chinese_Traditional": {
    "Translation": "優魯巴文",
    "ShouldTranslate": false
  },
  "Chinese_Simplified": {
    "Translation": "约鲁巴语",
    "ShouldTranslate": false
  },
  "ExportVersion": 1,
  "ImportVersion": 1,
  "name": "MainMenu.Matchmaking.Language.Yoruba",
  "internalEnabled": true,
  "persistentID": 447
}